rtl/perm.v
`timescale 1ns/1ps

module perm_check(
    input  wire       priv, // 0: User-space, 1: Supervisor-space
    input  wire       acc_load,
    input  wire       acc_store,
    input  wire       acc_ifetch,
    input  wire       pV,
    input  wire       pR,
    input  wire       pW,
    input  wire       pX,
    input  wire       pU,
    output wire       allow,
    output wire       pfault,
    output wire       xfault
);
    // User Mode Isolation Validation Rules
    wire privilege_valid = (~priv) ? (pU == 1'b1) : 1'b1;

    wire read_allowed    = acc_load   ? (pR & privilege_valid) : 1'b1;
    wire write_allowed   = acc_store  ? (pW & privilege_valid) : 1'b1;
    wire execute_allowed = acc_ifetch ? (pX & privilege_valid) : 1'b1;

    assign allow  = pV & read_allowed & write_allowed & execute_allowed;
    assign pfault = pV & privilege_valid & ((acc_load & ~pR) | (acc_store & ~pW));
    assign xfault = pV & privilege_valid & (acc_ifetch & ~pX);
endmodule

rtl/ptw.v
`timescale 1ns/1ps

module ptw #(
    parameter VAW = 32,
    parameter PAW = 32
)(
    input  wire        clk,
    input  wire        rst_n,
    input  wire        en,
    input  wire        miss_req,
    input  wire [19:0] miss_vpn,
    input  wire [7:0]  miss_asid,
    input  wire [19:0] satp_base_ppn,
    
    output reg         mem_req,
    output reg  [PAW-1:0] mem_addr,
    input  wire        mem_rdy,
    input  wire [31:0] mem_rdata,
    input  wire        mem_err,
    
    output reg         rf_valid,
    output reg  [19:0] rf_vpn,
    output reg  [7:0]  rf_asid,
    output reg  [19:0] rf_ppn,
    output reg         rf_r, rf_w, rf_x, rf_u, rf_v,
    output reg         bus_fault
);

    // PTW States
    localparam IDLE  = 2'b00;
    localparam LEVEL1 = 2'b01;
    localparam LEVEL0 = 2'b10;
    localparam FAULT  = 2'b11;

    reg [1:0] state, nstate;
    reg [3:0] watchdog_count; // Safety counter to prevent infinite hangs

    always @(*) begin
        nstate = state;
        case (state)
            IDLE: begin
                if (miss_req) nstate = LEVEL1;
            end
            LEVEL1: begin
                if (watchdog_count >= 4'd12) nstate = FAULT; // Loop breaker
                else if (mem_rdy) nstate = LEVEL0;
                else if (mem_err) nstate = FAULT;
            end
            LEVEL0: begin
                if (watchdog_count >= 4'd12) nstate = FAULT; // Loop breaker
                else if (mem_rdy) nstate = IDLE;
                else if (mem_err) nstate = FAULT;
            end
            FAULT: begin
                nstate = IDLE;
            end
            default: nstate = IDLE;
        endcase
    end

    always @(posedge clk or negedge rst_n) begin
        if (!rst_n) begin
            state          <= IDLE;
            mem_req        <= 1'b0;
            mem_addr       <= {PAW{1'b0}};
            rf_valid       <= 1'b0;
            rf_vpn         <= 20'b0;
            rf_asid        <= 8'b0;
            rf_ppn         <= 20'b0;
            {rf_r, rf_w, rf_x, rf_u, rf_v} <= 5'b0;
            bus_fault      <= 1'b0;
            watchdog_count <= 4'b0;
        end else if (en) begin
            state <= nstate;
            
            // Watchdog management
            if (state == LEVEL1 || state == LEVEL0) begin
                watchdog_count <= watchdog_count + 1'b1;
            end else begin
                watchdog_count <= 4'b0;
            end

            case (state)
                IDLE: begin
                    bus_fault <= 1'b0;
                    rf_valid  <= 1'b0;
                    if (miss_req) begin
                        mem_req  <= 1'b1;
                        mem_addr <= {satp_base_ppn, miss_vpn[19:10], 2'b00}; 
                    end
                end
                
                LEVEL1: begin
                    if (mem_rdy || watchdog_count >= 4'd12) begin
                        mem_addr <= {mem_rdata[29:10], miss_vpn[9:0], 2'b00};
                        if (watchdog_count >= 4'd12) mem_req <= 1'b0;
                    end
                end
                
                LEVEL0: begin
                    if (mem_rdy || watchdog_count >= 4'd12) begin
                        mem_req   <= 1'b0;
                        rf_valid  <= 1'b1;
                        rf_vpn    <= miss_vpn;
                        rf_asid   <= miss_asid;
                        rf_ppn    <= mem_rdata[29:10];
                        rf_v      <= mem_rdata[0];
                        rf_r      <= mem_rdata[1];
                        rf_w      <= mem_rdata[2];
                        rf_x      <= mem_rdata[3];
                        rf_u      <= mem_rdata[4];
                    end
                end
                
                FAULT: begin
                    mem_req   <= 1'b0;
                    bus_fault <= 1'b1;
                    rf_valid  <= 1'b0;
                end
            endcase
        end
    end
endmodule

rtl/tlb.v
`timescale 1ns/1ps

module tlb #(
    parameter VAW = 32,
    parameter PAW = 32,
    parameter ASIDW = 8,
    parameter SETS = 16,
    parameter WAYS = 4
)(
    input  wire                 clk,
    input  wire                 rst_n,
    input  wire                 en,
    // Lookup Interfaces
    input  wire [VAW-13:0]      vpn,
    input  wire [ASIDW-1:0]     asid,
    output reg                  hit,
    output reg  [PAW-13:0]      ppn,
    output reg                  perm_r,
    output reg                  perm_w,
    output reg                  perm_x,
    output reg                  perm_u,
    output reg                  valid,
    // Refill Interfaces
    input  wire                 refill,
    input  wire [VAW-13:0]      rf_vpn,
    input  wire [ASIDW-1:0]     rf_asid,
    input  wire [PAW-13:0]      rf_ppn,
    input  wire                 rf_r,
    input  wire                 rf_w,
    input  wire                 rf_x,
    input  wire                 rf_u,
    input  wire                 rf_v
);

    localparam IDXW = $clog2(SETS);
    localparam TAGW = (VAW - 12) - IDXW;

    wire [IDXW-1:0] idx = vpn[IDXW-1:0];
    wire [TAGW-1:0] lookup_tag = vpn[VAW-13:IDXW];

    // Core Internal Array Declarations
    reg [TAGW-1:0]   tag_array   [0:SETS-1][0:WAYS-1];
    reg [ASIDW-1:0]  asid_array  [0:SETS-1][0:WAYS-1];
    reg              vbit_array  [0:SETS-1][0:WAYS-1];
    reg [PAW-13:0]   ppn_array   [0:SETS-1][0:WAYS-1];
    reg              r_array     [0:SETS-1][0:WAYS-1];
    reg              w_array     [0:SETS-1][0:WAYS-1];
    reg              x_array     [0:SETS-1][0:WAYS-1];
    reg              u_array     [0:SETS-1][0:WAYS-1];
    
    // Pseudo-LRU age state arrays (3 bits per line array for 4-Ways)
    reg [WAYS-2:0]   plru        [0:SETS-1];

    integer w_idx;
    
    // Combinational Hit Detection Architecture
    always @(*) begin
        hit    = 1'b0;
        ppn    = {(PAW-12){1'b0}};
        perm_r = 1'b0;
        perm_w = 1'b0;
        perm_x = 1'b0;
        perm_u = 1'b0;
        valid  = 1'b0;
        
        for (w_idx = 0; w_idx < WAYS; w_idx = w_idx + 1) begin
            if (vbit_array[idx][w_idx] && 
                (tag_array[idx][w_idx] == lookup_tag) && 
                (asid_array[idx][w_idx] == asid)) begin
                
                hit    = 1'b1;
                ppn    = ppn_array[idx][w_idx];
                perm_r = r_array[idx][w_idx];
                perm_w = w_array[idx][w_idx];
                perm_x = x_array[idx][w_idx];
                perm_u = u_array[idx][w_idx];
                valid  = vbit_array[idx][w_idx];
            end
        end
    end

    // Tree Pseudo-LRU Target Calculation Functions
    function [WAYS-2:0] next_plru;
        input [WAYS-2:0] current_bits;
        input integer matched_way;
        begin
            next_plru = current_bits;
            if (matched_way < 2) begin
                next_plru[2] = 1'b1; // Direct toward right side
                next_plru[1] = (matched_way == 0) ? 1'b1 : 1'b0;
            end else begin
                next_plru[2] = 1'b0; // Direct toward left side
                next_plru[0] = (matched_way == 2) ? 1'b1 : 1'b0;
            end
        end
    endfunction

    function integer get_victim_way;
        input [WAYS-2:0] current_bits;
        begin
            if (current_bits[2] == 1'b0) begin
                get_victim_way = (current_bits[1] == 1'b0) ? 1 : 0;
            end else begin
                get_victim_way = (current_bits[0] == 1'b0) ? 3 : 2;
            end
        end
    endfunction

    integer s, w;
    integer target_victim;

    // Sequential State Transformations
    always @(posedge clk or negedge rst_n) begin
        if (!rst_n) begin
            for (s = 0; s < SETS; s = s + 1) begin
                plru[s] <= {(WAYS-1){1'b0}};
                for (w = 0; w < WAYS; w = w + 1) begin
                    vbit_array[s][w] <= 1'b0;
                    tag_array[s][w]  <= {TAGW{1'b0}};
                    asid_array[s][w] <= {ASIDW{1'b0}};
                    ppn_array[s][w]  <= {(PAW-12){1'b0}};
                    r_array[s][w]    <= 1'b0;
                    w_array[s][w]    <= 1'b0;
                    x_array[s][w]    <= 1'b0;
                    u_array[s][w]    <= 1'b0;
                end
            end
        end else if (en) begin
            if (hit) begin
                for (w = 0; w < WAYS; w = w + 1) begin
                    if (vbit_array[idx][w] && (tag_array[idx][w] == lookup_tag) && (asid_array[idx][w] == asid)) begin
                        plru[idx] <= next_plru(plru[idx], w);
                    end
                end
            end
            
            if (refill) begin
                target_victim = get_victim_way(plru[rf_vpn[IDXW-1:0]]);
                tag_array[rf_vpn[IDXW-1:0]][target_victim]  <= rf_vpn[VAW-13:IDXW];
                asid_array[rf_vpn[IDXW-1:0]][target_victim] <= rf_asid;
                ppn_array[rf_vpn[IDXW-1:0]][target_victim]  <= rf_ppn;
                r_array[rf_vpn[IDXW-1:0]][target_victim]    <= rf_r;
                w_array[rf_vpn[IDXW-1:0]][target_victim]    <= rf_w;
                x_array[rf_vpn[IDXW-1:0]][target_victim]    <= rf_x;
                u_array[rf_vpn[IDXW-1:0]][target_victim]    <= rf_u;
                vbit_array[rf_vpn[IDXW-1:0]][target_victim] <= rf_v;
                
                plru[rf_vpn[IDXW-1:0]] <= next_plru(plru[rf_vpn[IDXW-1:0]], target_victim);
            end
        end
    end
endmodule

rtl/mmu.v
`timescale 1ns/1ps

module mmu #(
    parameter VAW = 32,
    parameter PAW = 32,
    parameter ASIDW = 8,
    parameter SETS = 16,
    parameter WAYS = 4
)(
    input  wire               clk,
    input  wire               rst_n,
    input  wire               en,
    input  wire               translate_en,
    input  wire [PAW-13:0]    satp_base_ppn,
    input  wire [ASIDW-1:0]   csr_asid,
    input  wire               req_valid,
    input  wire [VAW-1:0]     req_va,
    input  wire [1:0]         req_acc,  
    input  wire               req_priv, 
    output reg                rsp_valid,
    output reg  [PAW-1:0]     rsp_pa,
    output reg                rsp_fault,
    output reg                rsp_xfault,
    output wire               mem_req,
    output wire [PAW-1:0]     mem_addr,
    input  wire               mem_rdy,
    input  wire [31:0]        mem_rdata,
    input  wire               mem_err
);

    wire [VAW-13:0] current_vpn = req_va[VAW-1:12];
    wire [11:0]     current_off = req_va[11:0];

    wire tlb_hit;
    wire [PAW-13:0] tlb_ppn;
    wire tlb_r, tlb_w, tlb_x, tlb_u, tlb_v;

    wire ptw_rf_valid;
    wire [VAW-13:0] ptw_rf_vpn;
    wire [ASIDW-1:0] ptw_rf_asid;
    wire [PAW-13:0] ptw_rf_ppn;
    wire ptw_rf_r, ptw_rf_w, ptw_rf_x, ptw_rf_u, ptw_rf_v;
    wire ptw_bus_fault;

    reg ptw_miss_req;

    tlb #(.VAW(VAW), .PAW(PAW), .ASIDW(ASIDW), .SETS(SETS), .WAYS(WAYS)) internal_tlb (
        .clk(clk), .rst_n(rst_n), .en(en),
        .vpn(current_vpn), .asid(csr_asid),
        .hit(tlb_hit), .ppn(tlb_ppn),
        .perm_r(tlb_r), .perm_w(tlb_w), .perm_x(tlb_x), .perm_u(tlb_u), .valid(tlb_v),
        .refill(ptw_rf_valid), .rf_vpn(ptw_rf_vpn), .rf_asid(ptw_rf_asid), .rf_ppn(ptw_rf_ppn),
        .rf_r(ptw_rf_r), .rf_w(ptw_rf_w), .rf_x(ptw_rf_x), .rf_u(ptw_rf_u), .rf_v(ptw_rf_v)
    );

    ptw #(.VAW(VAW), .PAW(PAW)) internal_ptw (
        .clk(clk), .rst_n(rst_n), .en(en),
        .miss_req(ptw_miss_req), .miss_vpn(current_vpn), .miss_asid(csr_asid), .satp_base_ppn(satp_base_ppn),
        .mem_req(mem_req), .mem_addr(mem_addr), .mem_rdy(mem_rdy), .mem_rdata(mem_rdata), .mem_err(mem_err),
        .rf_valid(ptw_rf_valid), .rf_vpn(ptw_rf_vpn), .rf_asid(ptw_rf_asid), .rf_ppn(ptw_rf_ppn),
        .rf_r(ptw_rf_r), .rf_w(ptw_rf_w), .rf_x(ptw_rf_x), .rf_u(ptw_rf_u), .rf_v(ptw_rf_v),
        .bus_fault(ptw_bus_fault)
    );

    wire acc_load   = (req_acc == 2'b01);
    wire acc_store  = (req_acc == 2'b10);
    wire acc_ifetch = (req_acc == 2'b00);

    wire perm_allow, perm_pfault, perm_xfault;
    
    wire active_v = tlb_hit ? tlb_v : ptw_rf_v;
    wire active_r = tlb_hit ? tlb_r : ptw_rf_r;
    wire active_w = tlb_hit ? tlb_w : ptw_rf_w;
    wire active_x = tlb_hit ? tlb_x : ptw_rf_x;
    wire active_u = tlb_hit ? tlb_u : ptw_rf_u;
    wire [PAW-13:0] active_ppn = tlb_hit ? tlb_ppn : ptw_rf_ppn;

    perm_check permissions_unit (
        .priv(req_priv), .acc_load(acc_load), .acc_store(acc_store), .acc_ifetch(acc_ifetch),
        .pV(active_v), .pR(active_r), .pW(active_w), .pX(active_x), .pU(active_u),
        .allow(perm_allow), .pfault(perm_pfault), .xfault(perm_xfault)
    );

    localparam MMU_IDLE = 2'b00;
    localparam MMU_WALK = 2'b01;
    localparam MMU_EVAL = 2'b10;

    reg [1:0] mmu_state, mmu_nstate;

    // Fixed FSM Logic
    always @(*) begin
        mmu_nstate = mmu_state;
        ptw_miss_req = 1'b0;
        case (mmu_state)
            MMU_IDLE: begin
                if (req_valid && translate_en) begin
                    if (tlb_hit) mmu_nstate = MMU_EVAL;
                    else begin
                        mmu_nstate = MMU_WALK;
                        ptw_miss_req = 1'b1;
                    end
                end
            end
            MMU_WALK: begin
                if (ptw_rf_valid) mmu_nstate = MMU_EVAL;
                else if (ptw_bus_fault) mmu_nstate = MMU_IDLE;
            end
            MMU_EVAL: begin
                mmu_nstate = MMU_IDLE;
            end
            default: mmu_nstate = MMU_IDLE;
        endcase
    end

    always @(posedge clk or negedge rst_n) begin
        if (!rst_n) begin
            mmu_state  <= MMU_IDLE;
            rsp_valid  <= 1'b0;
            rsp_pa     <= {PAW{1'b0}};
            rsp_fault  <= 1'b0;
            rsp_xfault <= 1'b0;
        end else if (en) begin
            mmu_state <= mmu_nstate;
            
            if (!translate_en && req_valid) begin
                rsp_valid  <= 1'b1;
                rsp_pa     <= req_va;
                rsp_fault  <= 1'b0;
                rsp_xfault <= 1'b0;
            end else if (!translate_en && !req_valid) begin
                rsp_valid  <= 1'b0;
            end else begin
                case (mmu_state)
                    MMU_IDLE: begin
                        rsp_valid <= 1'b0;
                    end
                    MMU_WALK: begin
                        if (ptw_bus_fault) begin
                            rsp_valid  <= 1'b1;
                            rsp_fault  <= 1'b1;
                            rsp_xfault <= 1'b0;
                        end
                    end
                    MMU_EVAL: begin
                        rsp_valid <= 1'b1;
                        if (perm_allow) begin
                            rsp_pa     <= {active_ppn, current_off};
                            rsp_fault  <= 1'b0;
                            rsp_xfault <= 1'b0;
                        end else begin
                            rsp_pa     <= {PAW{1'b0}};
                            rsp_fault  <= perm_pfault;
                            rsp_xfault <= perm_xfault;
                        end
                    end
                endcase
            end
        end
    end
endmodule

tb/mmu_tb.v
`timescale 1ns/1ps

module mmu_tb;
    reg clk;
    reg rst_n;
    reg en;
    reg translate_en;
    reg [19:0] satp_base_ppn;
    reg [7:0]  csr_asid;
    reg        req_valid;
    reg [31:0] req_va;
    reg [1:0]  req_acc;
    reg        req_priv;

    wire        rsp_valid;
    wire [31:0] rsp_pa;
    wire        rsp_fault;
    wire        rsp_xfault;
    wire        mem_req;
    wire [31:0] mem_addr;
    
    reg         mem_rdy;
    reg  [31:0] mem_rdata;
    reg         mem_err;

    integer file1, file2, file3, file4;

    // Clock Grid
    always #5 clk = ~clk;

    // DUT Instance
    mmu #(.VAW(32), .PAW(32)) dut (
        .clk(clk), .rst_n(rst_n), .en(en), .translate_en(translate_en),
        .satp_base_ppn(satp_base_ppn), .csr_asid(csr_asid),
        .req_valid(req_valid), .req_va(req_va), .req_acc(req_acc), .req_priv(req_priv),
        .rsp_valid(rsp_valid), .rsp_pa(rsp_pa), .rsp_fault(rsp_fault), .rsp_xfault(rsp_xfault),
        .mem_req(mem_req), .mem_addr(mem_addr), .mem_rdy(mem_rdy), .mem_rdata(mem_rdata), .mem_err(mem_err)
    );

    // Memory Model Emulator
    always @(posedge clk) begin
        if (!rst_n) begin
            mem_rdy   <= 1'b0;
            mem_rdata <= 32'h0;
            mem_err   <= 1'b0;
        end else if (mem_req) begin
            #1;
            mem_rdy   <= 1'b1;
            mem_rdata <= 32'h1000_000F; // Valid, R/W/X set
            mem_err   <= 1'b0;
        end else begin
            mem_rdy   <= 1'b0;
        end
    end

    initial begin
        $dumpfile("outputs/mmu.vcd");
        $dumpvars(0, mmu_tb);

        clk = 0; rst_n = 0; en = 1; translate_en = 1;
        satp_base_ppn = 20'h90000; csr_asid = 8'h01;
        req_valid = 0; req_va = 32'h0040_1000; req_acc = 2'b01; req_priv = 1'b1;

        #20; rst_n = 1; #20;

        // ==========================================
        // IMAGE CAPTURE 1: Cold Translation Walk
        // ==========================================
        $display("[TB] Running Scenario 1...");
        file1 = $fopen("outputs/wave_capture1.txt", "w");
        $fwrite(file1, "=== WAVE CAPTURE 1: COLD TRANSLATION (PTW WALK) ===\n");
        $fwrite(file1, "TIME(ns) | CLK | REQ_VALID | TRANSLATE_EN | RSP_VALID | FAULT\n");
        
        @(posedge clk); req_valid = 1'b1;
        repeat (8) begin
            @(posedge clk);
            $fwrite(file1, "%t  |  %b  |     %b     |      %b       |     %b     |   %b\n", $time, clk, req_valid, translate_en, rsp_valid, rsp_fault);
        end
        req_valid = 1'b0;
        $fclose(file1);
        #40;

        // ==========================================
        // IMAGE CAPTURE 2: TLB Cache Hot Hit
        // ==========================================
        $display("[TB] Running Scenario 2...");
        file2 = $fopen("outputs/wave_capture2.txt", "w");
        $fwrite(file2, "=== WAVE CAPTURE 2: TLB CACHE CACHED HIT ===\n");
        $fwrite(file2, "TIME(ns) | CLK | REQ_VALID | TLB_HIT | RSP_VALID | RSP_PA\n");
        
        req_valid = 1'b1;
        repeat (4) begin
            @(posedge clk);
            $fwrite(file2, "%t  |  %b  |     %b     |    %b    |     %b     | 0x%h\n", $time, clk, req_valid, dut.tlb_hit, rsp_valid, rsp_pa);
        end
        req_valid = 1'b0;
        $fclose(file2);
        #40;

        // ==========================================
        // IMAGE CAPTURE 3: User Privilege Fault
        // ==========================================
        $display("[TB] Running Scenario 3...");
        file3 = $fopen("outputs/wave_capture3.txt", "w");
        $fwrite(file3, "=== WAVE CAPTURE 3: PRIVILEGE PROTECTION FAULT ===\n");
        $fwrite(file3, "TIME(ns) | PRIV(1=S,0=U) | REQ_VALID | RSP_VALID | RSP_FAULT\n");
        
        req_priv = 1'b0; // Drop to User Mode
        req_valid = 1'b1;
        repeat (4) begin
            @(posedge clk);
            $fwrite(file3, "%t  |       %b       |     %b     |     %b     |     %b\n", $time, req_priv, req_valid, rsp_valid, rsp_fault);
        end
        req_valid = 1'b0;
        $fclose(file3);
        #40;

        // ==========================================
        // IMAGE CAPTURE 4: Bypass Translation Mode
        // ==========================================
        $display("[TB] Running Scenario 4...");
        file4 = $fopen("outputs/wave_capture4.txt", "w");
        $fwrite(file4, "=== WAVE CAPTURE 4: TRANSLATION BYPASS ===\n");
        $fwrite(file4, "TIME(ns) | TRANSLATE_EN | REQ_VA     | RSP_VALID | RSP_PA\n");
        
        translate_en = 1'b0; // Disable MMU Translation
        req_valid = 1'b1;
        req_va = 32'hAAAA_BBBB;
        repeat (4) begin
            @(posedge clk);
            $fwrite(file4, "%t  |      %b       | 0x%h |     %b     | 0x%h\n", $time, translate_en, req_va, rsp_valid, rsp_pa);
        end
        req_valid = 1'b0;
        $fclose(file4);

        $display("[TB EXECUTION] All 4 Image Captures generated successfully inside outputs/ folder.");
        $finish;
    end
endmodule

outputs/mmu.vcd
$date
	Sun Jun 21 17:34:12 2026
$end
$version
	Icarus Verilog
$end
$timescale
	1ps
$end
$scope module mmu_tb $end
$var wire 1 ! rsp_xfault $end
$var wire 1 " rsp_valid $end
$var wire 32 # rsp_pa [31:0] $end
$var wire 1 $ rsp_fault $end
$var wire 1 % mem_req $end
$var wire 32 & mem_addr [31:0] $end
$var reg 1 ' clk $end
$var reg 8 ( csr_asid [7:0] $end
$var reg 1 ) en $end
$var reg 1 * mem_err $end
$var reg 32 + mem_rdata [31:0] $end
$var reg 1 , mem_rdy $end
$var reg 2 - req_acc [1:0] $end
$var reg 1 . req_priv $end
$var reg 32 / req_va [31:0] $end
$var reg 1 0 req_valid $end
$var reg 1 1 rst_n $end
$var reg 20 2 satp_base_ppn [19:0] $end
$var reg 1 3 translate_en $end
$var integer 32 4 file1 [31:0] $end
$var integer 32 5 file2 [31:0] $end
$var integer 32 6 file3 [31:0] $end
$var integer 32 7 file4 [31:0] $end
$scope module dut $end
$var wire 1 ' clk $end
$var wire 8 8 csr_asid [7:0] $end
$var wire 1 ) en $end
$var wire 1 * mem_err $end
$var wire 32 9 mem_rdata [31:0] $end
$var wire 1 , mem_rdy $end
$var wire 2 : req_acc [1:0] $end
$var wire 1 . req_priv $end
$var wire 32 ; req_va [31:0] $end
$var wire 1 0 req_valid $end
$var wire 1 1 rst_n $end
$var wire 20 < satp_base_ppn [19:0] $end
$var wire 1 3 translate_en $end
$var wire 1 = tlb_x $end
$var wire 1 > tlb_w $end
$var wire 1 ? tlb_v $end
$var wire 1 @ tlb_u $end
$var wire 1 A tlb_r $end
$var wire 20 B tlb_ppn [19:0] $end
$var wire 1 C tlb_hit $end
$var wire 1 D ptw_rf_x $end
$var wire 1 E ptw_rf_w $end
$var wire 20 F ptw_rf_vpn [19:0] $end
$var wire 1 G ptw_rf_valid $end
$var wire 1 H ptw_rf_v $end
$var wire 1 I ptw_rf_u $end
$var wire 1 J ptw_rf_r $end
$var wire 20 K ptw_rf_ppn [19:0] $end
$var wire 8 L ptw_rf_asid [7:0] $end
$var wire 1 M ptw_bus_fault $end
$var wire 1 N perm_xfault $end
$var wire 1 O perm_pfault $end
$var wire 1 P perm_allow $end
$var wire 1 % mem_req $end
$var wire 32 Q mem_addr [31:0] $end
$var wire 20 R current_vpn [19:0] $end
$var wire 12 S current_off [11:0] $end
$var wire 1 T active_x $end
$var wire 1 U active_w $end
$var wire 1 V active_v $end
$var wire 1 W active_u $end
$var wire 1 X active_r $end
$var wire 20 Y active_ppn [19:0] $end
$var wire 1 Z acc_store $end
$var wire 1 [ acc_load $end
$var wire 1 \ acc_ifetch $end
$var parameter 32 ] ASIDW $end
$var parameter 2 ^ MMU_EVAL $end
$var parameter 2 _ MMU_IDLE $end
$var parameter 2 ` MMU_WALK $end
$var parameter 32 a PAW $end
$var parameter 32 b SETS $end
$var parameter 32 c VAW $end
$var parameter 32 d WAYS $end
$var reg 2 e mmu_nstate [1:0] $end
$var reg 2 f mmu_state [1:0] $end
$var reg 1 g ptw_miss_req $end
$var reg 1 $ rsp_fault $end
$var reg 32 h rsp_pa [31:0] $end
$var reg 1 " rsp_valid $end
$var reg 1 ! rsp_xfault $end
$scope module internal_ptw $end
$var wire 1 ' clk $end
$var wire 1 ) en $end
$var wire 1 * mem_err $end
$var wire 32 i mem_rdata [31:0] $end
$var wire 1 , mem_rdy $end
$var wire 8 j miss_asid [7:0] $end
$var wire 1 g miss_req $end
$var wire 20 k miss_vpn [19:0] $end
$var wire 1 1 rst_n $end
$var wire 20 l satp_base_ppn [19:0] $end
$var parameter 2 m FAULT $end
$var parameter 2 n IDLE $end
$var parameter 2 o LEVEL0 $end
$var parameter 2 p LEVEL1 $end
$var parameter 32 q PAW $end
$var parameter 32 r VAW $end
$var reg 1 M bus_fault $end
$var reg 32 s mem_addr [31:0] $end
$var reg 1 % mem_req $end
$var reg 2 t nstate [1:0] $end
$var reg 8 u rf_asid [7:0] $end
$var reg 20 v rf_ppn [19:0] $end
$var reg 1 J rf_r $end
$var reg 1 I rf_u $end
$var reg 1 H rf_v $end
$var reg 1 G rf_valid $end
$var reg 20 w rf_vpn [19:0] $end
$var reg 1 E rf_w $end
$var reg 1 D rf_x $end
$var reg 2 x state [1:0] $end
$var reg 4 y watchdog_count [3:0] $end
$upscope $end
$scope module internal_tlb $end
$var wire 8 z asid [7:0] $end
$var wire 1 ' clk $end
$var wire 1 ) en $end
$var wire 1 G refill $end
$var wire 8 { rf_asid [7:0] $end
$var wire 20 | rf_ppn [19:0] $end
$var wire 1 J rf_r $end
$var wire 1 I rf_u $end
$var wire 1 H rf_v $end
$var wire 20 } rf_vpn [19:0] $end
$var wire 1 E rf_w $end
$var wire 1 D rf_x $end
$var wire 1 1 rst_n $end
$var wire 20 ~ vpn [19:0] $end
$var wire 16 !" lookup_tag [15:0] $end
$var wire 4 "" idx [3:0] $end
$var parameter 32 #" ASIDW $end
$var parameter 32 $" IDXW $end
$var parameter 32 %" PAW $end
$var parameter 32 &" SETS $end
$var parameter 34 '" TAGW $end
$var parameter 32 (" VAW $end
$var parameter 32 )" WAYS $end
$var reg 1 C hit $end
$var reg 1 A perm_r $end
$var reg 1 @ perm_u $end
$var reg 1 > perm_w $end
$var reg 1 = perm_x $end
$var reg 20 *" ppn [19:0] $end
$var reg 1 ? valid $end
$var integer 32 +" s [31:0] $end
$var integer 32 ," target_victim [31:0] $end
$var integer 32 -" w [31:0] $end
$var integer 32 ." w_idx [31:0] $end
$scope function get_victim_way $end
$var reg 3 /" current_bits [2:0] $end
$upscope $end
$scope function next_plru $end
$var reg 3 0" current_bits [2:0] $end
$var integer 32 1" matched_way [31:0] $end
$upscope $end
$upscope $end
$scope module permissions_unit $end
$var wire 1 \ acc_ifetch $end
$var wire 1 [ acc_load $end
$var wire 1 Z acc_store $end
$var wire 1 P allow $end
$var wire 1 X pR $end
$var wire 1 W pU $end
$var wire 1 V pV $end
$var wire 1 U pW $end
$var wire 1 T pX $end
$var wire 1 O pfault $end
$var wire 1 . priv $end
$var wire 1 N xfault $end
$var wire 1 2" write_allowed $end
$var wire 1 3" read_allowed $end
$var wire 1 4" privilege_valid $end
$var wire 1 5" execute_allowed $end
$upscope $end
$upscope $end
$upscope $end
$enddefinitions $end
$comment Show the parameter values. $end
$dumpall
b100 )"
b100000 ("
b10000 '"
b10000 &"
b100000 %"
b100 $"
b1000 #"
b100000 r
b100000 q
b1 p
b10 o
b0 n
b11 m
b100 d
b100000 c
b10000 b
b100000 a
b1 `
b0 _
b10 ^
b1000 ]
$end
#0
$dumpvars
15"
14"
03"
12"
bx 1"
bx 0"
bx /"
b100 ."
b100 -"
bx ,"
b10000 +"
b0 *"
b1 ""
b1000000 !"
b10000000001 ~
b0 }
b0 |
b0 {
b1 z
b0 y
b0 x
b0 w
b0 v
b0 u
b0 t
b0 s
b10010000000000000000 l
b10000000001 k
b1 j
bx i
b0 h
0g
b0 f
b0 e
0\
1[
0Z
b0 Y
0X
0W
0V
0U
0T
b0 S
b10000000001 R
b0 Q
0P
0O
0N
0M
b0 L
b0 K
0J
0I
0H
0G
b0 F
0E
0D
0C
b0 B
0A
0@
0?
0>
0=
b10010000000000000000 <
b10000000001000000000000 ;
b1 :
bx 9
b1 8
bx 7
bx 6
bx 5
bx 4
13
b10010000000000000000 2
01
00
b10000000001000000000000 /
1.
b1 -
x,
bx +
x*
1)
b1 (
0'
b0 &
0%
0$
b0 #
0"
0!
$end
#5000
0*
b0 +
b0 9
b0 i
0,
b100 -"
b10000 +"
1'
#10000
0'
#15000
b100 -"
b10000 +"
1'
#20000
0'
11
#25000
1'
#30000
0'
#35000
1'
#40000
0'
b10000000000000000000000000000011 4
#45000
b1 t
1g
b1 e
10
1'
#50000
0'
#55000
0g
b10010000000000000000000000000100 &
b10010000000000000000000000000100 Q
b10010000000000000000000000000100 s
1%
b1 x
b1 f
1'
#60000
0'
#65000
b1 y
1'
#66000
b10 t
b10000000000000000000000001111 +
b10000000000000000000000001111 9
b10000000000000000000000001111 i
1,
#70000
0'
#75000
b0 t
b1000000000000000000000000000100 &
b1000000000000000000000000000100 Q
b1000000000000000000000000000100 s
b10 y
b10 x
1'
#80000
0'
#85000
1P
13"
0O
1T
1U
1X
1V
b1000000000000000000 Y
b10 e
1D
1E
1J
1H
b1000000000000000000 K
b1000000000000000000 v
b1000000000000000000 |
b1 L
b1 u
b1 {
b10000000001 F
b10000000001 w
b10000000001 }
1G
0%
b11 y
b0 x
1'
#90000
0'
#95000
1?
1=
1>
1A
b1000000000000000000 B
b1000000000000000000 *"
1C
b100 ."
b0 e
0G
b0 y
b10 f
0,
b0 0"
b1 1"
b1 ,"
b0 /"
1'
#100000
0'
#105000
b10 e
b1000000000000000000000000000000 #
b1000000000000000000000000000000 h
1"
b0 f
b100 0"
b100 -"
1'
#110000
0'
#115000
b0 e
0"
b10 f
b100 -"
1'
#120000
0'
#125000
1"
b0 f
b0 e
b100 -"
00
1'
#130000
0'
#135000
0"
b100 -"
1'
#140000
0'
#145000
b100 -"
1'
#150000
0'
#155000
b100 -"
1'
#160000
0'
#165000
b10 f
b100 -"
b0 e
1'
10
b10000000000000000000000000000011 5
#170000
0'
#175000
b10 e
1"
b0 f
b100 -"
1'
#180000
0'
#185000
b0 e
0"
b10 f
b100 -"
1'
#190000
0'
#195000
1"
b0 f
b0 e
b100 -"
00
1'
#200000
0'
#205000
0"
b100 -"
1'
#210000
0'
#215000
b100 -"
1'
#220000
0'
#225000
b100 -"
1'
#230000
0'
#235000
b10 f
0P
03"
04"
b100 -"
b0 e
1'
10
0.
b10000000000000000000000000000011 6
#240000
0'
#245000
b10 e
b0 #
b0 h
1"
b0 f
b100 -"
1'
#250000
0'
#255000
b0 e
0"
b10 f
b100 -"
1'
#260000
0'
#265000
1"
b0 f
b0 e
b100 -"
00
1'
#270000
0'
#275000
0"
b100 -"
1'
#280000
0'
#285000
b100 -"
1'
#290000
0'
#295000
b100 -"
1'
#300000
0'
